model_scraper/__init__.py
model_scraper/model.py
model_scraper/model_scraper.py
model_scraper-1.0.0.dist-info/METADATA
model_scraper-1.0.0.dist-info/WHEEL
model_scraper-1.0.0.dist-info/top_level.txt
model_scraper-1.0.0.dist-info/RECORD
